vl_saliency/__init__.py
vl_saliency/_version.py
vl_saliency/core/__init__.py
vl_saliency/core/_types.py
vl_saliency/core/extractor.py
vl_saliency/core/map.py
vl_saliency/core/trace.py
vl_saliency/lib/__init__.py
vl_saliency/lib/cam.py
vl_saliency/selectors/__init__.py
vl_saliency/selectors/base.py
vl_saliency/selectors/indexing.py
vl_saliency/selectors/re.py
vl_saliency/transforms/__init__.py
vl_saliency/transforms/functional.py
vl_saliency/transforms/layers.py
vl_saliency/transforms/localization.py
vl_saliency/transforms/pipe.py
vl_saliency/transforms/spatial.py
vl_saliency/utils/__init__.py
vl_saliency/utils/logger.py
vl_saliency/utils/transformer_utils.py
vl_saliency/viz/__init__.py
vl_saliency/viz/overlay.py
vl_saliency/viz/tokens.py
vl_saliency-1.1.6.dist-info/licenses/LICENSE
vl_saliency-1.1.6.dist-info/METADATA
vl_saliency-1.1.6.dist-info/WHEEL
vl_saliency-1.1.6.dist-info/top_level.txt
vl_saliency-1.1.6.dist-info/RECORD
