Metadata-Version: 2.4
Name: vl-saliency
Version: 1.1.6
Summary: Text-to-Image Attention Visualization for Vision-Language Models.
Author: Alexander Brady, Tim Eilers
License: MIT License
Project-URL: github, https://github.com/alexander-brady/vl-saliency
Requires-Python: >=3.11
License-File: LICENSE
Requires-Dist: matplotlib>=3.10.7
Requires-Dist: pillow>=12.0.0
Requires-Dist: scipy>=1.15.3
Requires-Dist: torch>=2.8.0
Dynamic: license-file
